a2lmodel/__init__.py
a2lmodel/a2l_model.py
a2lmodel-0.0.2.dist-info/licenses/LICENSE
a2lmodel-0.0.2.dist-info/METADATA
a2lmodel-0.0.2.dist-info/WHEEL
a2lmodel-0.0.2.dist-info/top_level.txt
a2lmodel-0.0.2.dist-info/RECORD
