Metadata-Version: 2.4
Name: a2lmodel
Version: 0.0.2
Summary: Parse and model ASAP2 A2L files with bidirectional conversion
Author-email: Sgnes <sgnes0514@gmail.com>
License-Expression: MIT
Project-URL: Homepage, https://github.com/sgnes/PyA2lModel
Project-URL: Bug Reports, https://github.com/sgnes/PyA2lModel/issues
Project-URL: Source, https://github.com/sgnes/PyA2lModel
Keywords: asap2,a2l,parser,automotive,ecul,xcp,calibration
Classifier: Development Status :: 3 - Alpha
Classifier: Intended Audience :: Developers
Classifier: Operating System :: OS Independent
Classifier: Programming Language :: Python :: 3
Classifier: Programming Language :: Python :: 3.8
Classifier: Programming Language :: Python :: 3.9
Classifier: Programming Language :: Python :: 3.10
Classifier: Programming Language :: Python :: 3.11
Classifier: Programming Language :: Python :: 3.12
Classifier: Topic :: Software Development :: Libraries :: Python Modules
Classifier: Topic :: Scientific/Engineering
Classifier: Topic :: Utilities
Requires-Python: >=3.8
License-File: LICENSE
Provides-Extra: dev
Requires-Dist: pytest>=6.0; extra == "dev"
Requires-Dist: pytest-cov; extra == "dev"
Requires-Dist: black; extra == "dev"
Requires-Dist: isort; extra == "dev"
Requires-Dist: flake8; extra == "dev"
Requires-Dist: mypy; extra == "dev"
Dynamic: license-file
